{
  "current": {
    "container_width": 1340,
    "section_header_alignment": "left",
    "section_header_alignment_mobile": "center",
    "page_transition": true,
    "animations": "fade-in-left",
    "color_primary": "#222222",
    "color_border": "#eeeeee",
    "color_body_text": "#222222",
    "color_heading_text": "#222222",
    "color_main_bg": "#ffffff",
    "color_secondary_bg": "#f6f6f6",
    "color_field_bg": "#ffffff",
    "color_btn_secondary_text": "#222222",
    "color_btn_bg_hover": "#222222",
    "color_header_text": "#222222",
    "color_header_text_transparent": "#222222",
    "color_menu_subtext": "#222222",
    "color_menu_dropdown_bg": "#ffffff",
    "color_product_price": "#222222",
    "color_badge_sale": "#b70a0a",
    "color_badge_hot": "#222222",
    "color_badge_new": "#207758",
    "color_badge_soldout": "#222222",
    "color_cart_bubble": "#222222",
    "color_overlay_bg": "#222222",
    "type_body_font": "akko_n4",
    "body_scale": 100,
    "type_header_font": "inter_n6",
    "heading_scale": 100,
    "heading_mobile_scale": 75,
    "heading_uppercase": false,
    "menu_font": "heading",
    "btn_font": "body",
    "btn_rounded": 4,
    "upper_btn_label": true,
    "predictive_search_collection": "all",
    "show_free_shipping_message": true,
    "free_shipping_message": "Spend {{amount}} more for free shipping",
    "free_shipping_limit": "500",
    "pcard_image_ratio": "1\/1",
    "pcard_show_second_img": true,
    "pcard_show_color_swatch": true,
    "pcard_show_review_badge": false,
    "pcard_show_badge_soldout": false,
    "pcard_show_sale_badge": false,
    "pcard_upper_title": false,
    "color_swatches_enable": true,
    "color_swatches_shape": "circle",
    "custom_colors": "Black: #000,\nWhite: #fff,\nRosin: #36362d,\nRustic Brown: #a85502,\nDark Red: #502b33,\nWalnut: #786a5f,\nPurple: #705861,\nBlack: #000000,\nMolten Lava: #b5332e,\nPine Grove: #213631,\nIvy Green: #5b7763,\nMaroon Red: #740f35,\nBuckthorn Brown: #ffdb58,\nDark Blue: #123850,\nBrown: #743500,\nScarab: #23312d,\nLight Brown: #d5b89b,\nArgan: #213631,\nGrey: #dddddd,\nDark Brown: #440004,\nBeige: #e7d8bf,\nDark Orange: #b5520e,\nMuesli: #ddd5bc,\nFudge: #493338,\nCognac: #8b645a,\nPine Green: #21694a,\nDark Coffee: #4a342e,\nRed Wine: #582b36,\nAsh Blue: #d1dfeb,\nLight Oatmeal: #f7efdf,\nDark Indigo: #1f0954,\nBlue Horizon: #8eb3d1,\nFeather Grey: #b8ad9e,\nAsh Blonde: #d7bea5,\nLight Indigo: #93b8cd,\nMedium Indigo: #3953a4,\nDeep Red: #8c2e23",
    "social_facebook_link": "https:\/\/www.facebook.com\/people\/Tiny-Memory-%E5%BE%AE%E5%BD%B1%E5%8D%B0%E8%A8%98\/100088326999655\/",
    "social_instagram_link": "https:\/\/www.instagram.com\/hktiny.memory\/",
    "social_whatsapp_link": "https:\/\/api.whatsapp.com\/send\/?phone=85256332221",
    "currency_code_enabled": false,
    "cb_design_mode": true,
    "fluid_container_width": 1330,
    "fluid_offset": 55,
    "narrow_container_width": 800,
    "heading_font_size": "h2",
    "section_header_transform": "capitalize",
    "menu_weight": "500",
    "btn_weight": "500",
    "btn_transform": "uppercase",
    "pcard_alignment": "center",
    "pcard_on_sale_badge": "show_text",
    "article_show_excerpt": true,
    "show_agree_on_product": false,
    "font_base_size": 15,
    "color_btn_bg": "#0532c1",
    "color_annbar_bg": "#222222",
    "color_footer_text": "#000000",
    "color_link_hover": "#000000",
    "color_compare_price": "#909090",
    "color_menu_text_hover": "#000000",
    "color_topbar_text_hover": "#000000",
    "colors_solid_button_labels": "#FFFFFF",
    "colors_accent_1": "#121212",
    "colors_accent_2": "#334FB4",
    "colors_text": "#121212",
    "colors_outline_button_labels": "#121212",
    "colors_background_1": "#FFFFFF",
    "colors_background_2": "#F3F3F3",
    "sections": {
      "sticky-atc-bar": {
        "type": "sticky-atc-bar",
        "settings": {
          "container": "container",
          "show_on_desktop": true,
          "show_on_mobile": true,
          "show_atc_button": true,
          "show_dynamic_checkout_buttons": true,
          "show_quantity": true
        }
      },
      "product-collection-description": {
        "type": "product-collection-description",
        "settings": {
        }
      }
    },
    "content_for_index": [

    ],
    "blocks": {
      "14847459021641295842": {
        "type": "shopify:\/\/apps\/custom-product-designer-studio\/blocks\/product_designer\/77c0b81f-7286-46a5-80e2-582b8f3a6f4d",
        "disabled": false,
        "settings": {
        }
      }
    }
  },
  "presets": {
    "Fleek": {
      "page_transition": true,
      "animations": "fade-in-up",
      "container_width": 1340,
      "section_header_alignment": "left",
      "section_header_alignment_mobile": "center",
      "color_primary": "#222222",
      "color_border": "#eeeeee",
      "color_body_text": "#222222",
      "color_heading_text": "#222222",
      "color_secondary_bg": "#f6f6f6",
      "color_field_bg": "#ffffff",
      "color_btn_secondary_text": "#222222",
      "color_btn_bg_hover": "#222222",
      "color_header_text": "#222222",
      "color_header_text_transparent": "#222222",
      "color_menu_subtext": "#222222",
      "color_menu_dropdown_bg": "#ffffff",
      "color_product_price": "#222222",
      "color_badge_sale": "#b70a0a",
      "color_badge_hot": "#222222",
      "color_badge_new": "#207758",
      "color_badge_soldout": "#222222",
      "color_cart_bubble": "#222222",
      "color_overlay_bg": "#222222",
      "type_body_font": "inter_n4",
      "body_scale": 100,
      "type_header_font": "inter_n6",
      "heading_scale": 100,
      "heading_mobile_scale": 80,
      "menu_font": "heading",
      "btn_font": "heading",
      "btn_rounded": 4,
      "upper_btn_label": false,
      "predictive_search_collection": "all",
      "show_free_shipping_message": true,
      "pcard_show_second_img": true,
      "pcard_show_color_swatch": true,
      "pcard_show_review_badge": false,
      "pcard_show_badge_soldout": false,
      "pcard_show_sale_badge": false,
      "color_swatches_enable": true,
      "custom_colors": "Black: #000,\nWhite: #fff,\nRosin: #36362d,\nRustic Brown: #a85502,\nDark Red: #502b33,\nWalnut: #786a5f,\nPurple: #705861,\nBlack: #000000,\nMolten Lava: #b5332e,\nPine Grove: #213631,\nIvy Green: #5b7763,\nMaroon Red: #740f35,\nBuckthorn Brown: #ffdb58,\nDark Blue: #123850,\nBrown: #743500,\nScarab: #23312d,\nLight Brown: #d5b89b,\nArgan: #213631,\nGrey: #dddddd,\nDark Brown: #440004,\nBeige: #e7d8bf,\nDark Orange: #b5520e,\nMuesli: #ddd5bc,\nFudge: #493338,\nCognac: #8b645a,\nPine Green: #21694a,\nDark Coffee: #4a342e,\nRed Wine: #582b36,\nAsh Blue: #d1dfeb,\nLight Oatmeal: #f7efdf,\nDark Indigo: #1f0954,\nBlue Horizon: #8eb3d1,\nFeather Grey: #b8ad9e,\nAsh Blonde: #d7bea5,\nLight Indigo: #93b8cd,\nMedium Indigo: #3953a4,\nDeep Red: #8c2e23",
      "currency_code_enabled": false,
      "fluid_container_width": 1330,
      "fluid_offset": 55,
      "narrow_container_width": 800,
      "heading_font_size": "h2",
      "section_header_transform": "capitalize",
      "menu_weight": "500",
      "btn_weight": "500",
      "btn_transform": "uppercase",
      "pcard_alignment": "center",
      "pcard_on_sale_badge": "show_text",
      "article_show_excerpt": true,
      "show_agree_on_product": false,
      "font_base_size": 15,
      "color_btn_bg": "#0532c1",
      "color_annbar_bg": "#222222",
      "color_footer_text": "#000000",
      "color_link_hover": "#000000",
      "color_compare_price": "#909090",
      "color_menu_text_hover": "#000000",
      "color_topbar_text_hover": "#000000",
      "colors_solid_button_labels": "#FFFFFF",
      "colors_accent_1": "#121212",
      "colors_accent_2": "#334FB4",
      "colors_text": "#121212",
      "colors_outline_button_labels": "#121212",
      "colors_background_1": "#FFFFFF",
      "colors_background_2": "#F3F3F3",
      "sections": {
        "sticky-atc-bar": {
          "type": "sticky-atc-bar",
          "settings": {
            "container": "container",
            "show_on_desktop": true,
            "show_on_mobile": true,
            "show_atc_button": true,
            "show_dynamic_checkout_buttons": false,
            "show_quantity": true
          }
        }
      }
    },
    "Gusto": {
      "page_transition": true,
      "animations": "fade-in-up",
      "container_width": 1170,
      "section_header_alignment": "center",
      "color_primary": "#273820",
      "color_border": "#dfdfdf",
      "color_heading_text": "#222222",
      "color_secondary_bg": "#f3f3f3",
      "color_field_bg": "#ffffff",
      "color_btn_secondary_text": "#222222",
      "color_btn_bg_hover": "#1e3315",
      "color_header_text": "#222222",
      "color_header_text_transparent": "#ffffff",
      "color_menu_dropdown_bg": "#ffffff",
      "color_product_price": "#000000",
      "color_badge_sale": "#a83d3d",
      "color_badge_soldout": "#222222",
      "color_cart_bubble": "#222222",
      "type_body_font": "avenir_next_n5",
      "body_scale": 100,
      "type_header_font": "avenir_next_n6",
      "heading_scale": 100,
      "heading_uppercase": true,
      "menu_font": "heading",
      "btn_font": "heading",
      "btn_rounded": 0,
      "upper_btn_label": true,
      "predictive_search_collection": "all",
      "pcard_upper_title": true,
      "color_swatches_enable": true,
      "custom_colors": "brown: #964B00,\nblack: #000000,\nsilver: #c0c0c0,\ngreen: #00FF00,\norange: #fe9001,\npink: #FFC0CB,\ngrey: #808080,\nsand: #D8D1C4,\ndark blue: #40495d,\napricot: #c48c39,\ngold: #d8b268,\nnavy: #272931,,\nsage: #b1ad88,\nmedium blue: #0000cd,\nseagreen: #2e8b57,\nfirebrick: #b22222,\nsteel blue: #4682b4,\nwheat: #f5deb3,\nlightsky blue: #87cefa",
      "heading_font_size": "h4",
      "section_header_weight": "600",
      "section_header_transform": "uppercase",
      "menu_weight": "600",
      "btn_weight": "600",
      "btn_transform": "uppercase",
      "pcard_title_text_transform": "upper",
      "pcard_on_sale_badge": "show_text",
      "pcard_title_line_clamp": "unset",
      "article_show_excerpt": true,
      "spacing_sections": 80,
      "font_base_size": 15,
      "heading_1_size": 40,
      "heading_2_size": 38,
      "heading_3_size": 28,
      "heading_4_size": 26,
      "heading_5_size": 18,
      "heading_6_size": 16,
      "mobile_heading_scale": 80,
      "color_btn_bg": "#273820",
      "color_annbar_bg": "#242e20",
      "color_subtext": "#000000",
      "color_compare_price": "#909090",
      "teaser_popup_bg": "#222222",
      "colors_solid_button_labels": "#FFFFFF",
      "colors_accent_1": "#121212",
      "colors_accent_2": "#334FB4",
      "colors_text": "#121212",
      "colors_outline_button_labels": "#121212",
      "colors_background_1": "#FFFFFF",
      "colors_background_2": "#F3F3F3",
      "sections": {
        "sticky-atc-bar": {
          "type": "sticky-atc-bar",
          "settings": {
            "container": "container",
            "show_on_desktop": true,
            "show_on_mobile": true,
            "show_atc_button": true,
            "show_dynamic_checkout_buttons": false,
            "show_quantity": true
          }
        }
      },
      "content_for_index": [

      ]
    },
    "Flairy": {
      "page_transition": true,
      "animations": "fade-in-up",
      "container_width": 1140,
      "section_header_alignment": "center",
      "color_primary": "#1437aa",
      "color_border": "#eeeeee",
      "color_body_text": "#222222",
      "color_heading_text": "#222222",
      "color_secondary_bg": "#f6f6f6",
      "color_field_bg": "rgba(0,0,0,0)",
      "color_btn_secondary_text": "#222222",
      "color_btn_bg_hover": "#062fb2",
      "color_header_text": "#222222",
      "color_header_text_transparent": "#222222",
      "color_menu_subtext": "#000000",
      "color_menu_dropdown_bg": "#ffffff",
      "color_badge_sale": "#d01c1c",
      "type_body_font": "ibm_plex_sans_n4",
      "type_header_font": "ibm_plex_sans_n5",
      "heading_scale": 100,
      "menu_font": "heading",
      "btn_font": "heading",
      "btn_rounded": 0,
      "upper_btn_label": true,
      "predictive_search_collection": "all",
      "pcard_show_second_img": true,
      "pcard_show_color_swatch": true,
      "pcard_show_review_badge": false,
      "color_swatches_enable": true,
      "custom_colors": "",
      "currency_code_enabled": false,
      "fluid_container_width": 1330,
      "fluid_offset": 55,
      "narrow_container_width": 800,
      "heading_font_size": "h2",
      "section_header_transform": "capitalize",
      "menu_weight": "500",
      "btn_weight": "500",
      "btn_transform": "uppercase",
      "pcard_alignment": "center",
      "pcard_on_sale_badge": "show_text",
      "article_show_excerpt": true,
      "show_agree_on_product": false,
      "font_base_size": 15,
      "color_btn_bg": "#0532c1",
      "color_annbar_bg": "#222222",
      "color_footer_text": "#000000",
      "color_link_hover": "#000000",
      "color_compare_price": "#909090",
      "color_menu_text_hover": "#000000",
      "color_topbar_text_hover": "#000000",
      "colors_solid_button_labels": "#FFFFFF",
      "colors_accent_1": "#121212",
      "colors_accent_2": "#334FB4",
      "colors_text": "#121212",
      "colors_outline_button_labels": "#121212",
      "colors_background_1": "#FFFFFF",
      "colors_background_2": "#F3F3F3",
      "sections": {
        "sticky-atc-bar": {
          "type": "sticky-atc-bar",
          "settings": {
            "container": "container",
            "show_on_desktop": true,
            "show_on_mobile": true,
            "show_atc_button": true,
            "show_dynamic_checkout_buttons": false,
            "show_quantity": true
          }
        }
      },
      "content_for_index": [

      ]
    },
    "Cosmo": {
      "page_transition": true,
      "animations": "fade-in-up",
      "container_width": 1170,
      "section_header_alignment": "center",
      "color_primary": "#e17855",
      "color_border": "#eeeeee",
      "color_body_text": "#222222",
      "color_secondary_bg": "#f8f6f4",
      "color_field_bg": "#ffffff",
      "color_btn_secondary_text": "#222222",
      "color_btn_bg_hover": "#d6613b",
      "color_btn_text_hover": "#fff",
      "color_product_price": "#222222",
      "color_badge_sale": "#e17855",
      "color_badge_soldout": "#a0a0a0",
      "color_cart_bubble": "#e17855",
      "type_body_font": "karla_n4",
      "body_scale": 106,
      "type_header_font": "crimson_text_n4",
      "heading_scale": 114,
      "btn_rounded": 0,
      "upper_btn_label": true,
      "predictive_search_collection": "all",
      "cart_icon": "shopping-cart",
      "pcard_show_vendor": false,
      "pcard_show_review_badge": false,
      "pcard_show_cart_button": true,
      "pcard_show_quickview_button": true,
      "pcard_show_badge_soldout": true,
      "color_swatches_enable": true,
      "fluid_container_width": 1330,
      "fluid_offset": 50,
      "narrow_container_width": 800,
      "heading_letter_space": 0,
      "heading_font_size": "h3",
      "section_header_weight": "400",
      "section_header_transform": "initial",
      "menu_weight": "500",
      "btn_weight": "500",
      "btn_transform": "uppercase",
      "pcard_alignment": "center",
      "pcard_on_sale_badge": "show_text",
      "pcard_title_size": "h5",
      "pcard_title_line_clamp": "unset",
      "article_image_aspect_ratio": "adapt",
      "article_show_date": true,
      "article_show_excerpt": true,
      "article_show_readmore": true,
      "font_base_size": 15,
      "heading_5_size": 22,
      "heading_6_size": 20,
      "color_btn_bg": "#e17855",
      "color_annbar_bg": "#f5f2f0",
      "color_annbar_text": "#000000",
      "color_btn_secondary_border": "#f0f0f0",
      "color_compare_price": "#888888",
      "teaser_popup_bg": "#222222",
      "colors_solid_button_labels": "#FFFFFF",
      "colors_accent_1": "#121212",
      "colors_accent_2": "#334FB4",
      "colors_text": "#121212",
      "colors_outline_button_labels": "#121212",
      "colors_background_1": "#FFFFFF",
      "colors_background_2": "#F3F3F3",
      "sections": {
        "sticky-atc-bar": {
          "type": "sticky-atc-bar",
          "settings": {
            "container": "container",
            "show_on_desktop": true,
            "show_on_mobile": true,
            "show_atc_button": true,
            "show_dynamic_checkout_buttons": false,
            "show_quantity": true
          }
        }
      },
      "content_for_index": [

      ]
    }
  },
  "platform_customizations": {
    "custom_css": [

    ]
  }
}
